Workbook

Sheet INPUT
A1: GSTR-3B INTEREST (LATE FILING) – INPUTS
A3: Assumptions:
A4: 1) Payment date is assumed as GSTR-3B filing date (proxy).
A5: 2) Interest computed on CASH paid portion (IGST/CGST/SGST) for belated return cases.
A6: 3) Due dates & relief rules are table-driven. Add/maintain CBIC overrides in masters for completeness.
A7: 4) State Group is auto-derived from GSTIN; user override not required.
A9: Row | B9: GSTIN (User) | C9: Period Type (MONTH/QUARTER) | D9: Period Key (YYYY-MM or YYYY-Q1..Q4) | E9: Filer Type (MONTHLY/QRMP) | F9: State Group (A=22nd / B=24th / NA) | G9: Turnover Class (LE_5CR/GT_5CR/ANY) | H9: Filing Date (DD-MM-YYYY) | I9: Cash Paid IGST | J9: Cash Paid CGST | K9: Cash Paid SGST | L9: Notes (optional) | M9: Derived Period Start Date | N9: Derived Quarter End Date | O9: Validate Inputs
A10: 1 | F10: =IF(B10="","NA",IF(OR(LEFT(B10,2)="35",LEFT(B10,2)="26",LEFT(B10,2)="25",LEFT(B10,2)="31",LEFT(B10,2)="34"),"A","B")) -> NA | M10: =IF(C10="","",IF(B10="MONTH",DATE(VALUE(LEFT(C10,4)),VALUE(MID(C10,6,2)),1),IF(B10="QUARTER",CHOOSE(VALUE(RIGHT(C10,1)),DATE(VALUE(LEFT(C10,4)),4,1),DATE(VALUE(LEFT(C10,4)),7,1),DATE(VALUE(LEFT(C10,4)),10,1),DATE(VALUE(LEFT(C10,4)),1,1)),""))) | N10: =IF(C10="","",IF(B10<>"QUARTER","",CHOOSE(VALUE(RIGHT(C10,1)),DATE(VALUE(LEFT(C10,4)),6,30),DATE(VALUE(LEFT(C10,4)),9,30),DATE(VALUE(LEFT(C10,4)),12,31),DATE(VALUE(LEFT(C10,4))+1,3,31)))) | O10: =IF(C10="","",IF(OR(G10="",D10=""),"MISSING: Filing Date or Filer Type",IF(AND(B10="MONTH",LEN(C10)<>7),"BAD Period Key (YYYY-MM)",IF(AND(B10="QUARTER",LEN(C10)<>7),"BAD Period Key (YYYY-Q#)","OK"))))
A11: 2 | F11: =IF(B11="","NA",IF(OR(LEFT(B11,2)="35",LEFT(B11,2)="26",LEFT(B11,2)="25",LEFT(B11,2)="31",LEFT(B11,2)="34"),"A","B")) -> NA | M11: =IF(C11="","",IF(B11="MONTH",DATE(VALUE(LEFT(C11,4)),VALUE(MID(C11,6,2)),1),IF(B11="QUARTER",CHOOSE(VALUE(RIGHT(C11,1)),DATE(VALUE(LEFT(C11,4)),4,1),DATE(VALUE(LEFT(C11,4)),7,1),DATE(VALUE(LEFT(C11,4)),10,1),DATE(VALUE(LEFT(C11,4)),1,1)),""))) | N11: =IF(C11="","",IF(B11<>"QUARTER","",CHOOSE(VALUE(RIGHT(C11,1)),DATE(VALUE(LEFT(C11,4)),6,30),DATE(VALUE(LEFT(C11,4)),9,30),DATE(VALUE(LEFT(C11,4)),12,31),DATE(VALUE(LEFT(C11,4))+1,3,31)))) | O11: =IF(C11="","",IF(OR(G11="",D11=""),"MISSING: Filing Date or Filer Type",IF(AND(B11="MONTH",LEN(C11)<>7),"BAD Period Key (YYYY-MM)",IF(AND(B11="QUARTER",LEN(C11)<>7),"BAD Period Key (YYYY-Q#)","OK"))))
A12: 3 | F12: =IF(B12="","NA",IF(OR(LEFT(B12,2)="35",LEFT(B12,2)="26",LEFT(B12,2)="25",LEFT(B12,2)="31",LEFT(B12,2)="34"),"A","B")) -> NA | M12: =IF(C12="","",IF(B12="MONTH",DATE(VALUE(LEFT(C12,4)),VALUE(MID(C12,6,2)),1),IF(B12="QUARTER",CHOOSE(VALUE(RIGHT(C12,1)),DATE(VALUE(LEFT(C12,4)),4,1),DATE(VALUE(LEFT(C12,4)),7,1),DATE(VALUE(LEFT(C12,4)),10,1),DATE(VALUE(LEFT(C12,4)),1,1)),""))) | N12: =IF(C12="","",IF(B12<>"QUARTER","",CHOOSE(VALUE(RIGHT(C12,1)),DATE(VALUE(LEFT(C12,4)),6,30),DATE(VALUE(LEFT(C12,4)),9,30),DATE(VALUE(LEFT(C12,4)),12,31),DATE(VALUE(LEFT(C12,4))+1,3,31)))) | O12: =IF(C12="","",IF(OR(G12="",D12=""),"MISSING: Filing Date or Filer Type",IF(AND(B12="MONTH",LEN(C12)<>7),"BAD Period Key (YYYY-MM)",IF(AND(B12="QUARTER",LEN(C12)<>7),"BAD Period Key (YYYY-Q#)","OK"))))
A13: 4 | F13: =IF(B13="","NA",IF(OR(LEFT(B13,2)="35",LEFT(B13,2)="26",LEFT(B13,2)="25",LEFT(B13,2)="31",LEFT(B13,2)="34"),"A","B")) -> NA | M13: =IF(C13="","",IF(B13="MONTH",DATE(VALUE(LEFT(C13,4)),VALUE(MID(C13,6,2)),1),IF(B13="QUARTER",CHOOSE(VALUE(RIGHT(C13,1)),DATE(VALUE(LEFT(C13,4)),4,1),DATE(VALUE(LEFT(C13,4)),7,1),DATE(VALUE(LEFT(C13,4)),10,1),DATE(VALUE(LEFT(C13,4)),1,1)),""))) | N13: =IF(C13="","",IF(B13<>"QUARTER","",CHOOSE(VALUE(RIGHT(C13,1)),DATE(VALUE(LEFT(C13,4)),6,30),DATE(VALUE(LEFT(C13,4)),9,30),DATE(VALUE(LEFT(C13,4)),12,31),DATE(VALUE(LEFT(C13,4))+1,3,31)))) | O13: =IF(C13="","",IF(OR(G13="",D13=""),"MISSING: Filing Date or Filer Type",IF(AND(B13="MONTH",LEN(C13)<>7),"BAD Period Key (YYYY-MM)",IF(AND(B13="QUARTER",LEN(C13)<>7),"BAD Period Key (YYYY-Q#)","OK"))))
A14: 5 | F14: =IF(B14="","NA",IF(OR(LEFT(B14,2)="35",LEFT(B14,2)="26",LEFT(B14,2)="25",LEFT(B14,2)="31",LEFT(B14,2)="34"),"A","B")) -> NA | M14: =IF(C14="","",IF(B14="MONTH",DATE(VALUE(LEFT(C14,4)),VALUE(MID(C14,6,2)),1),IF(B14="QUARTER",CHOOSE(VALUE(RIGHT(C14,1)),DATE(VALUE(LEFT(C14,4)),4,1),DATE(VALUE(LEFT(C14,4)),7,1),DATE(VALUE(LEFT(C14,4)),10,1),DATE(VALUE(LEFT(C14,4)),1,1)),""))) | N14: =IF(C14="","",IF(B14<>"QUARTER","",CHOOSE(VALUE(RIGHT(C14,1)),DATE(VALUE(LEFT(C14,4)),6,30),DATE(VALUE(LEFT(C14,4)),9,30),DATE(VALUE(LEFT(C14,4)),12,31),DATE(VALUE(LEFT(C14,4))+1,3,31)))) | O14: =IF(C14="","",IF(OR(G14="",D14=""),"MISSING: Filing Date or Filer Type",IF(AND(B14="MONTH",LEN(C14)<>7),"BAD Period Key (YYYY-MM)",IF(AND(B14="QUARTER",LEN(C14)<>7),"BAD Period Key (YYYY-Q#)","OK"))))
A15: 6 | F15: =IF(B15="","NA",IF(OR(LEFT(B15,2)="35",LEFT(B15,2)="26",LEFT(B15,2)="25",LEFT(B15,2)="31",LEFT(B15,2)="34"),"A","B")) -> NA | M15: =IF(C15="","",IF(B15="MONTH",DATE(VALUE(LEFT(C15,4)),VALUE(MID(C15,6,2)),1),IF(B15="QUARTER",CHOOSE(VALUE(RIGHT(C15,1)),DATE(VALUE(LEFT(C15,4)),4,1),DATE(VALUE(LEFT(C15,4)),7,1),DATE(VALUE(LEFT(C15,4)),10,1),DATE(VALUE(LEFT(C15,4)),1,1)),""))) | N15: =IF(C15="","",IF(B15<>"QUARTER","",CHOOSE(VALUE(RIGHT(C15,1)),DATE(VALUE(LEFT(C15,4)),6,30),DATE(VALUE(LEFT(C15,4)),9,30),DATE(VALUE(LEFT(C15,4)),12,31),DATE(VALUE(LEFT(C15,4))+1,3,31)))) | O15: =IF(C15="","",IF(OR(G15="",D15=""),"MISSING: Filing Date or Filer Type",IF(AND(B15="MONTH",LEN(C15)<>7),"BAD Period Key (YYYY-MM)",IF(AND(B15="QUARTER",LEN(C15)<>7),"BAD Period Key (YYYY-Q#)","OK"))))
A16: 7 | F16: =IF(B16="","NA",IF(OR(LEFT(B16,2)="35",LEFT(B16,2)="26",LEFT(B16,2)="25",LEFT(B16,2)="31",LEFT(B16,2)="34"),"A","B")) -> NA | M16: =IF(C16="","",IF(B16="MONTH",DATE(VALUE(LEFT(C16,4)),VALUE(MID(C16,6,2)),1),IF(B16="QUARTER",CHOOSE(VALUE(RIGHT(C16,1)),DATE(VALUE(LEFT(C16,4)),4,1),DATE(VALUE(LEFT(C16,4)),7,1),DATE(VALUE(LEFT(C16,4)),10,1),DATE(VALUE(LEFT(C16,4)),1,1)),""))) | N16: =IF(C16="","",IF(B16<>"QUARTER","",CHOOSE(VALUE(RIGHT(C16,1)),DATE(VALUE(LEFT(C16,4)),6,30),DATE(VALUE(LEFT(C16,4)),9,30),DATE(VALUE(LEFT(C16,4)),12,31),DATE(VALUE(LEFT(C16,4))+1,3,31)))) | O16: =IF(C16="","",IF(OR(G16="",D16=""),"MISSING: Filing Date or Filer Type",IF(AND(B16="MONTH",LEN(C16)<>7),"BAD Period Key (YYYY-MM)",IF(AND(B16="QUARTER",LEN(C16)<>7),"BAD Period Key (YYYY-Q#)","OK"))))
A17: 8 | F17: =IF(B17="","NA",IF(OR(LEFT(B17,2)="35",LEFT(B17,2)="26",LEFT(B17,2)="25",LEFT(B17,2)="31",LEFT(B17,2)="34"),"A","B")) -> NA | M17: =IF(C17="","",IF(B17="MONTH",DATE(VALUE(LEFT(C17,4)),VALUE(MID(C17,6,2)),1),IF(B17="QUARTER",CHOOSE(VALUE(RIGHT(C17,1)),DATE(VALUE(LEFT(C17,4)),4,1),DATE(VALUE(LEFT(C17,4)),7,1),DATE(VALUE(LEFT(C17,4)),10,1),DATE(VALUE(LEFT(C17,4)),1,1)),""))) | N17: =IF(C17="","",IF(B17<>"QUARTER","",CHOOSE(VALUE(RIGHT(C17,1)),DATE(VALUE(LEFT(C17,4)),6,30),DATE(VALUE(LEFT(C17,4)),9,30),DATE(VALUE(LEFT(C17,4)),12,31),DATE(VALUE(LEFT(C17,4))+1,3,31)))) | O17: =IF(C17="","",IF(OR(G17="",D17=""),"MISSING: Filing Date or Filer Type",IF(AND(B17="MONTH",LEN(C17)<>7),"BAD Period Key (YYYY-MM)",IF(AND(B17="QUARTER",LEN(C17)<>7),"BAD Period Key (YYYY-Q#)","OK"))))
A18: 9 | F18: =IF(B18="","NA",IF(OR(LEFT(B18,2)="35",LEFT(B18,2)="26",LEFT(B18,2)="25",LEFT(B18,2)="31",LEFT(B18,2)="34"),"A","B")) -> NA | M18: =IF(C18="","",IF(B18="MONTH",DATE(VALUE(LEFT(C18,4)),VALUE(MID(C18,6,2)),1),IF(B18="QUARTER",CHOOSE(VALUE(RIGHT(C18,1)),DATE(VALUE(LEFT(C18,4)),4,1),DATE(VALUE(LEFT(C18,4)),7,1),DATE(VALUE(LEFT(C18,4)),10,1),DATE(VALUE(LEFT(C18,4)),1,1)),""))) | N18: =IF(C18="","",IF(B18<>"QUARTER","",CHOOSE(VALUE(RIGHT(C18,1)),DATE(VALUE(LEFT(C18,4)),6,30),DATE(VALUE(LEFT(C18,4)),9,30),DATE(VALUE(LEFT(C18,4)),12,31),DATE(VALUE(LEFT(C18,4))+1,3,31)))) | O18: =IF(C18="","",IF(OR(G18="",D18=""),"MISSING: Filing Date or Filer Type",IF(AND(B18="MONTH",LEN(C18)<>7),"BAD Period Key (YYYY-MM)",IF(AND(B18="QUARTER",LEN(C18)<>7),"BAD Period Key (YYYY-Q#)","OK"))))
A19: 10 | F19: =IF(B19="","NA",IF(OR(LEFT(B19,2)="35",LEFT(B19,2)="26",LEFT(B19,2)="25",LEFT(B19,2)="31",LEFT(B19,2)="34"),"A","B")) -> NA | M19: =IF(C19="","",IF(B19="MONTH",DATE(VALUE(LEFT(C19,4)),VALUE(MID(C19,6,2)),1),IF(B19="QUARTER",CHOOSE(VALUE(RIGHT(C19,1)),DATE(VALUE(LEFT(C19,4)),4,1),DATE(VALUE(LEFT(C19,4)),7,1),DATE(VALUE(LEFT(C19,4)),10,1),DATE(VALUE(LEFT(C19,4)),1,1)),""))) | N19: =IF(C19="","",IF(B19<>"QUARTER","",CHOOSE(VALUE(RIGHT(C19,1)),DATE(VALUE(LEFT(C19,4)),6,30),DATE(VALUE(LEFT(C19,4)),9,30),DATE(VALUE(LEFT(C19,4)),12,31),DATE(VALUE(LEFT(C19,4))+1,3,31)))) | O19: =IF(C19="","",IF(OR(G19="",D19=""),"MISSING: Filing Date or Filer Type",IF(AND(B19="MONTH",LEN(C19)<>7),"BAD Period Key (YYYY-MM)",IF(AND(B19="QUARTER",LEN(C19)<>7),"BAD Period Key (YYYY-Q#)","OK"))))
A20: 11 | F20: =IF(B20="","NA",IF(OR(LEFT(B20,2)="35",LEFT(B20,2)="26",LEFT(B20,2)="25",LEFT(B20,2)="31",LEFT(B20,2)="34"),"A","B")) -> NA | M20: =IF(C20="","",IF(B20="MONTH",DATE(VALUE(LEFT(C20,4)),VALUE(MID(C20,6,2)),1),IF(B20="QUARTER",CHOOSE(VALUE(RIGHT(C20,1)),DATE(VALUE(LEFT(C20,4)),4,1),DATE(VALUE(LEFT(C20,4)),7,1),DATE(VALUE(LEFT(C20,4)),10,1),DATE(VALUE(LEFT(C20,4)),1,1)),""))) | N20: =IF(C20="","",IF(B20<>"QUARTER","",CHOOSE(VALUE(RIGHT(C20,1)),DATE(VALUE(LEFT(C20,4)),6,30),DATE(VALUE(LEFT(C20,4)),9,30),DATE(VALUE(LEFT(C20,4)),12,31),DATE(VALUE(LEFT(C20,4))+1,3,31)))) | O20: =IF(C20="","",IF(OR(G20="",D20=""),"MISSING: Filing Date or Filer Type",IF(AND(B20="MONTH",LEN(C20)<>7),"BAD Period Key (YYYY-MM)",IF(AND(B20="QUARTER",LEN(C20)<>7),"BAD Period Key (YYYY-Q#)","OK"))))
A21: 12 | F21: =IF(B21="","NA",IF(OR(LEFT(B21,2)="35",LEFT(B21,2)="26",LEFT(B21,2)="25",LEFT(B21,2)="31",LEFT(B21,2)="34"),"A","B")) -> NA | M21: =IF(C21="","",IF(B21="MONTH",DATE(VALUE(LEFT(C21,4)),VALUE(MID(C21,6,2)),1),IF(B21="QUARTER",CHOOSE(VALUE(RIGHT(C21,1)),DATE(VALUE(LEFT(C21,4)),4,1),DATE(VALUE(LEFT(C21,4)),7,1),DATE(VALUE(LEFT(C21,4)),10,1),DATE(VALUE(LEFT(C21,4)),1,1)),""))) | N21: =IF(C21="","",IF(B21<>"QUARTER","",CHOOSE(VALUE(RIGHT(C21,1)),DATE(VALUE(LEFT(C21,4)),6,30),DATE(VALUE(LEFT(C21,4)),9,30),DATE(VALUE(LEFT(C21,4)),12,31),DATE(VALUE(LEFT(C21,4))+1,3,31)))) | O21: =IF(C21="","",IF(OR(G21="",D21=""),"MISSING: Filing Date or Filer Type",IF(AND(B21="MONTH",LEN(C21)<>7),"BAD Period Key (YYYY-MM)",IF(AND(B21="QUARTER",LEN(C21)<>7),"BAD Period Key (YYYY-Q#)","OK"))))
... A69: 60 | F69: =IF(B69="","NA",IF(OR(LEFT(B69,2)="35",LEFT(B69,2)="26",LEFT(B69,2)="25",LEFT(B69,2)="31",LEFT(B69,2)="34"),"A","B")) -> NA | M69: =IF(C69="","",IF(B69="MONTH",DATE(VALUE(LEFT(C69,4)),VALUE(MID(C69,6,2)),1),IF(B69="QUARTER",CHOOSE(VALUE(RIGHT(C69,1)),DATE(VALUE(LEFT(C69,4)),4,1),DATE(VALUE(LEFT(C69,4)),7,1),DATE(VALUE(LEFT(C69,4)),10,1),DATE(VALUE(LEFT(C69,4)),1,1)),""))) | N69: =IF(C69="","",IF(B69<>"QUARTER","",CHOOSE(VALUE(RIGHT(C69,1)),DATE(VALUE(LEFT(C69,4)),6,30),DATE(VALUE(LEFT(C69,4)),9,30),DATE(VALUE(LEFT(C69,4)),12,31),DATE(VALUE(LEFT(C69,4))+1,3,31)))) | O69: =IF(C69="","",IF(OR(G69="",D69=""),"MISSING: Filing Date or Filer Type",IF(AND(B69="MONTH",LEN(C69)<>7),"BAD Period Key (YYYY-MM)",IF(AND(B69="QUARTER",LEN(C69)<>7),"BAD Period Key (YYYY-Q#)","OK"))))
F70: =IF(B70="","NA",IF(OR(LEFT(B70,2)="35",LEFT(B70,2)="26",LEFT(B70,2)="25",LEFT(B70,2)="31",LEFT(B70,2)="34"),"A","B")) -> NA
F71: =IF(B71="","NA",IF(OR(LEFT(B71,2)="35",LEFT(B71,2)="26",LEFT(B71,2)="25",LEFT(B71,2)="31",LEFT(B71,2)="34"),"A","B")) -> NA
F72: =IF(B72="","NA",IF(OR(LEFT(B72,2)="35",LEFT(B72,2)="26",LEFT(B72,2)="25",LEFT(B72,2)="31",LEFT(B72,2)="34"),"A","B")) -> NA
F73: =IF(B73="","NA",IF(OR(LEFT(B73,2)="35",LEFT(B73,2)="26",LEFT(B73,2)="25",LEFT(B73,2)="31",LEFT(B73,2)="34"),"A","B")) -> NA
F74: =IF(B74="","NA",IF(OR(LEFT(B74,2)="35",LEFT(B74,2)="26",LEFT(B74,2)="25",LEFT(B74,2)="31",LEFT(B74,2)="34"),"A","B")) -> NA
F75: =IF(B75="","NA",IF(OR(LEFT(B75,2)="35",LEFT(B75,2)="26",LEFT(B75,2)="25",LEFT(B75,2)="31",LEFT(B75,2)="34"),"A","B")) -> NA
F76: =IF(B76="","NA",IF(OR(LEFT(B76,2)="35",LEFT(B76,2)="26",LEFT(B76,2)="25",LEFT(B76,2)="31",LEFT(B76,2)="34"),"A","B")) -> NA
F77: =IF(B77="","NA",IF(OR(LEFT(B77,2)="35",LEFT(B77,2)="26",LEFT(B77,2)="25",LEFT(B77,2)="31",LEFT(B77,2)="34"),"A","B")) -> NA
F78: =IF(B78="","NA",IF(OR(LEFT(B78,2)="35",LEFT(B78,2)="26",LEFT(B78,2)="25",LEFT(B78,2)="31",LEFT(B78,2)="34"),"A","B")) -> NA
F79: =IF(B79="","NA",IF(OR(LEFT(B79,2)="35",LEFT(B79,2)="26",LEFT(B79,2)="25",LEFT(B79,2)="31",LEFT(B79,2)="34"),"A","B")) -> NA
F80: =IF(B80="","NA",IF(OR(LEFT(B80,2)="35",LEFT(B80,2)="26",LEFT(B80,2)="25",LEFT(B80,2)="31",LEFT(B80,2)="34"),"A","B")) -> NA
F81: =IF(B81="","NA",IF(OR(LEFT(B81,2)="35",LEFT(B81,2)="26",LEFT(B81,2)="25",LEFT(B81,2)="31",LEFT(B81,2)="34"),"A","B")) -> NA
... F199: =IF(B199="","NA",IF(OR(LEFT(B199,2)="35",LEFT(B199,2)="26",LEFT(B199,2)="25",LEFT(B199,2)="31",LEFT(B199,2)="34"),"A","B")) -> NA

Sheet DUE_DATE_MASTER
A1: DUE DATE MASTER (Effective Due Dates after CBIC extensions/notifications)
A3: How to use:
A4: Add period-specific override rows below whenever CBIC extends the due date for that period.
A5: If no override exists, CALC uses default due date: Monthly=20th next month; QRMP=22nd/24th next month after quarter.
A8: Period Type | B8: Period Key | C8: Filer Type | D8: State Group | E8: Effective Due Date | F8: Priority | G8: CBIC Reference | H8: Remarks | I8: Key (helper)
A9: MONTH | B9: 2017-07 | C9: MONTHLY | D9: NA | E9: 42967 | F9: 10 | G9: Default Rule (Sec 39) | H9: Standard monthly due date | I9: =A9&"|"&B9&"|"&C9&"|"&D9 -> MONTH|2017-07|MONTHLY|NA
A10: MONTH | B10: 2017-08 | C10: MONTHLY | D10: NA | E10: 42998 | F10: 10 | G10: Default Rule (Sec 39) | H10: Standard monthly due date | I10: =A10&"|"&B10&"|"&C10&"|"&D10 -> MONTH|2017-08|MONTHLY|NA
A11: MONTH | B11: 2017-09 | C11: MONTHLY | D11: NA | E11: 43028 | F11: 10 | G11: Default Rule (Sec 39) | H11: Standard monthly due date | I11: =A11&"|"&B11&"|"&C11&"|"&D11 -> MONTH|2017-09|MONTHLY|NA
A12: MONTH | B12: 2017-10 | C12: MONTHLY | D12: NA | E12: 43059 | F12: 10 | G12: Default Rule (Sec 39) | H12: Standard monthly due date | I12: =A12&"|"&B12&"|"&C12&"|"&D12 -> MONTH|2017-10|MONTHLY|NA
A13: MONTH | B13: 2017-11 | C13: MONTHLY | D13: NA | E13: 43089 | F13: 10 | G13: Default Rule (Sec 39) | H13: Standard monthly due date | I13: =A13&"|"&B13&"|"&C13&"|"&D13 -> MONTH|2017-11|MONTHLY|NA
A14: MONTH | B14: 2017-12 | C14: MONTHLY | D14: NA | E14: 43120 | F14: 10 | G14: Default Rule (Sec 39) | H14: Standard monthly due date | I14: =A14&"|"&B14&"|"&C14&"|"&D14 -> MONTH|2017-12|MONTHLY|NA
A15: MONTH | B15: 2018-01 | C15: MONTHLY | D15: NA | E15: 43151 | F15: 10 | G15: Default Rule (Sec 39) | H15: Standard monthly due date | I15: =A15&"|"&B15&"|"&C15&"|"&D15 -> MONTH|2018-01|MONTHLY|NA
A16: MONTH | B16: 2018-02 | C16: MONTHLY | D16: NA | E16: 43179 | F16: 10 | G16: Default Rule (Sec 39) | H16: Standard monthly due date | I16: =A16&"|"&B16&"|"&C16&"|"&D16 -> MONTH|2018-02|MONTHLY|NA
A17: MONTH | B17: 2018-03 | C17: MONTHLY | D17: NA | E17: 43210 | F17: 10 | G17: Default Rule (Sec 39) | H17: Standard monthly due date | I17: =A17&"|"&B17&"|"&C17&"|"&D17 -> MONTH|2018-03|MONTHLY|NA
A18: MONTH | B18: 2018-04 | C18: MONTHLY | D18: NA | E18: 43240 | F18: 10 | G18: Default Rule (Sec 39) | H18: Standard monthly due date | I18: =A18&"|"&B18&"|"&C18&"|"&D18 -> MONTH|2018-04|MONTHLY|NA
A19: MONTH | B19: 2018-05 | C19: MONTHLY | D19: NA | E19: 43271 | F19: 10 | G19: Default Rule (Sec 39) | H19: Standard monthly due date | I19: =A19&"|"&B19&"|"&C19&"|"&D19 -> MONTH|2018-05|MONTHLY|NA
A20: MONTH | B20: 2018-06 | C20: MONTHLY | D20: NA | E20: 43301 | F20: 10 | G20: Default Rule (Sec 39) | H20: Standard monthly due date | I20: =A20&"|"&B20&"|"&C20&"|"&D20 -> MONTH|2018-06|MONTHLY|NA
... A188: MONTH | B188: 2021-05 | C188: MONTHLY | D188: NA | E188: 44397 | F188: 1 | G188: Notif 18/2021 | H188: COVID second wave | I188: =A188&"|"&B188&"|"&C188&"|"&D188 -> MONTH|2021-05|MONTHLY|NA

Sheet INTEREST_RELIEF_RULES
A1: INTEREST RELIEF RULES (Reduced / Nil interest slabs as per CBIC notifications/circulars)
A3: Rule matching:
A4: Engine picks first matching rule by lowest Priority. If no rule matches, default 18% p.a. applies.
A5: If Eligibility Cutoff is set and Filing Date is after it, the rule is ignored (default 18% applies).
A8: Priority | B8: Period Type | C8: From Period Key | D8: To Period Key | E8: Filer Type (MONTHLY/QRMP/ANY) | F8: Turnover Class (LE_5CR/GT_5CR/ANY) | G8: Eligibility Cutoff Filing Date (optional) | H8: Slab1 Days | I8: Slab1 Rate p.a. | J8: Slab2 Days | K8: Slab2 Rate p.a. | L8: Slab3 Rate p.a. (remaining) | M8: CBIC Reference | N8: Notes
A9: 1 | B9: MONTH | C9: 2020-02 | D9: 2020-04 | E9: MONTHLY | F9: GT_5CR | G9: 2020-06-24 | H9: 15 | I9: 0 | J9: 9999 | K9: 0.09 | L9: 0.18 | M9: Notif 31/2020 & Circular 136/06/2020 | N9: Nil 15 days then 9% thereafter if filed by cutoff; else 18%
A10: 1 | B10: MONTH | C10: 2020-02 | D10: 2020-04 | E10: MONTHLY | F10: LE_5CR | G10: 2020-06-24 | H10: 15 | I10: 0 | J10: 9999 | K10: 0.09 | L10: 0.18 | M10: Notif 31/2020 & Circular 136/06/2020 | N10: Nil 15 days then 9% thereafter if filed by cutoff; else 18%
A11: 1 | B11: MONTH | C11: 2021-03 | D11: 2021-05 | E11: MONTHLY | F11: GT_5CR | H11: 15 | I11: 0 | J11: 45 | K11: 0.09 | L11: 0.18 | M11: Notif 18/2021-Central Tax | N11: Typical slab; verify exact days per notification table
A12: 1 | B12: MONTH | C12: 2021-03 | D12: 2021-05 | E12: MONTHLY | F12: LE_5CR | H12: 15 | I12: 0 | J12: 60 | K12: 0.09 | L12: 0.18 | M12: Notif 18/2021-Central Tax | N12: Typical slab; verify exact days per notification table
A13: 1 | B13: QUARTER | C13: 2021-Q4 | D13: 2021-Q4 | E13: QRMP | F13: ANY | H13: 15 | I13: 0 | J13: 45 | K13: 0.09 | L13: 0.18 | M13: Notif 18/2021-Central Tax | N13: Quarter ending Mar-2021 relief; verify exact applicability

Sheet CALC
A1: CALCULATION (Interest on late filing of GSTR-3B – head-wise)
A3: Row | B3: Period Type | C3: Period Key | D3: Filer Type | E3: State Group | F3: Turnover Class | G3: Filing Date | H3: Due Date (Effective) | I3: Delay Days | J3: Cash IGST | K3: Cash CGST | L3: Cash SGST | M3: Rule Applied (Ref) | N3: Slab1 Days Used | O3: Slab2 Days Used | P3: IGST Interest | Q3: CGST Interest | R3: SGST Interest | S3: Total Interest
A4: =INPUT!A10 -> 1 | B4: =INPUT!B10 -> 0 | C4: =INPUT!C10 -> 0 | D4: =INPUT!D10 -> 0 | E4: =INPUT!E10 -> 0 | F4: =INPUT!F10 -> NA | G4: =INPUT!G10 -> 0 | H4: =IF(C4="","",IFERROR(_xludf.XLOOKUP(B4&"|"&C4&"|"&D4&"|"&E4,DUE_DATE_MASTER!I:I,DUE_DATE_MASTER!E:E,""),IF(B4="MONTH",DATE(VALUE(LEFT(C4,4)),VALUE(MID(C4,6,2))+1,20),IF(B4="QUARTER",DATE(YEAR(EOMONTH(INPUT!M10,0)),MONTH(EOMONTH(INPUT!M10,0))+1,IF(E4="A",22,24)),"")))) | I4: =IF(OR(G4="",H4=""),"",MAX(0,G4-H4)) | J4: =INPUT!H10 -> 0 | K4: =INPUT!I10 -> 0 | L4: =INPUT!J10 -> 0 | S4: =IF(P4="","",P4+Q4+R4)
A5: =INPUT!A11 -> 2 | B5: =INPUT!B11 -> 0 | C5: =INPUT!C11 -> 0 | D5: =INPUT!D11 -> 0 | E5: =INPUT!E11 -> 0 | F5: =INPUT!F11 -> NA | G5: =INPUT!G11 -> 0 | H5: =IF(C5="","",IFERROR(_xludf.XLOOKUP(B5&"|"&C5&"|"&D5&"|"&E5,DUE_DATE_MASTER!I:I,DUE_DATE_MASTER!E:E,""),IF(B5="MONTH",DATE(VALUE(LEFT(C5,4)),VALUE(MID(C5,6,2))+1,20),IF(B5="QUARTER",DATE(YEAR(EOMONTH(INPUT!M11,0)),MONTH(EOMONTH(INPUT!M11,0))+1,IF(E5="A",22,24)),"")))) | I5: =IF(OR(G5="",H5=""),"",MAX(0,G5-H5)) | J5: =INPUT!H11 -> 0 | K5: =INPUT!I11 -> 0 | L5: =INPUT!J11 -> 0 | S5: =IF(P5="","",P5+Q5+R5)
A6: =INPUT!A12 -> 3 | B6: =INPUT!B12 -> 0 | C6: =INPUT!C12 -> 0 | D6: =INPUT!D12 -> 0 | E6: =INPUT!E12 -> 0 | F6: =INPUT!F12 -> NA | G6: =INPUT!G12 -> 0 | H6: =IF(C6="","",IFERROR(_xludf.XLOOKUP(B6&"|"&C6&"|"&D6&"|"&E6,DUE_DATE_MASTER!I:I,DUE_DATE_MASTER!E:E,""),IF(B6="MONTH",DATE(VALUE(LEFT(C6,4)),VALUE(MID(C6,6,2))+1,20),IF(B6="QUARTER",DATE(YEAR(EOMONTH(INPUT!M12,0)),MONTH(EOMONTH(INPUT!M12,0))+1,IF(E6="A",22,24)),"")))) | I6: =IF(OR(G6="",H6=""),"",MAX(0,G6-H6)) | J6: =INPUT!H12 -> 0 | K6: =INPUT!I12 -> 0 | L6: =INPUT!J12 -> 0 | S6: =IF(P6="","",P6+Q6+R6)
A7: =INPUT!A13 -> 4 | B7: =INPUT!B13 -> 0 | C7: =INPUT!C13 -> 0 | D7: =INPUT!D13 -> 0 | E7: =INPUT!E13 -> 0 | F7: =INPUT!F13 -> NA | G7: =INPUT!G13 -> 0 | H7: =IF(C7="","",IFERROR(_xludf.XLOOKUP(B7&"|"&C7&"|"&D7&"|"&E7,DUE_DATE_MASTER!I:I,DUE_DATE_MASTER!E:E,""),IF(B7="MONTH",DATE(VALUE(LEFT(C7,4)),VALUE(MID(C7,6,2))+1,20),IF(B7="QUARTER",DATE(YEAR(EOMONTH(INPUT!M13,0)),MONTH(EOMONTH(INPUT!M13,0))+1,IF(E7="A",22,24)),"")))) | I7: =IF(OR(G7="",H7=""),"",MAX(0,G7-H7)) | J7: =INPUT!H13 -> 0 | K7: =INPUT!I13 -> 0 | L7: =INPUT!J13 -> 0 | S7: =IF(P7="","",P7+Q7+R7)
A8: =INPUT!A14 -> 5 | B8: =INPUT!B14 -> 0 | C8: =INPUT!C14 -> 0 | D8: =INPUT!D14 -> 0 | E8: =INPUT!E14 -> 0 | F8: =INPUT!F14 -> NA | G8: =INPUT!G14 -> 0 | H8: =IF(C8="","",IFERROR(_xludf.XLOOKUP(B8&"|"&C8&"|"&D8&"|"&E8,DUE_DATE_MASTER!I:I,DUE_DATE_MASTER!E:E,""),IF(B8="MONTH",DATE(VALUE(LEFT(C8,4)),VALUE(MID(C8,6,2))+1,20),IF(B8="QUARTER",DATE(YEAR(EOMONTH(INPUT!M14,0)),MONTH(EOMONTH(INPUT!M14,0))+1,IF(E8="A",22,24)),"")))) | I8: =IF(OR(G8="",H8=""),"",MAX(0,G8-H8)) | J8: =INPUT!H14 -> 0 | K8: =INPUT!I14 -> 0 | L8: =INPUT!J14 -> 0 | S8: =IF(P8="","",P8+Q8+R8)
A9: =INPUT!A15 -> 6 | B9: =INPUT!B15 -> 0 | C9: =INPUT!C15 -> 0 | D9: =INPUT!D15 -> 0 | E9: =INPUT!E15 -> 0 | F9: =INPUT!F15 -> NA | G9: =INPUT!G15 -> 0 | H9: =IF(C9="","",IFERROR(_xludf.XLOOKUP(B9&"|"&C9&"|"&D9&"|"&E9,DUE_DATE_MASTER!I:I,DUE_DATE_MASTER!E:E,""),IF(B9="MONTH",DATE(VALUE(LEFT(C9,4)),VALUE(MID(C9,6,2))+1,20),IF(B9="QUARTER",DATE(YEAR(EOMONTH(INPUT!M15,0)),MONTH(EOMONTH(INPUT!M15,0))+1,IF(E9="A",22,24)),"")))) | I9: =IF(OR(G9="",H9=""),"",MAX(0,G9-H9)) | J9: =INPUT!H15 -> 0 | K9: =INPUT!I15 -> 0 | L9: =INPUT!J15 -> 0 | S9: =IF(P9="","",P9+Q9+R9)
A10: =INPUT!A16 -> 7 | B10: =INPUT!B16 -> 0 | C10: =INPUT!C16 -> 0 | D10: =INPUT!D16 -> 0 | E10: =INPUT!E16 -> 0 | F10: =INPUT!F16 -> NA | G10: =INPUT!G16 -> 0 | H10: =IF(C10="","",IFERROR(_xludf.XLOOKUP(B10&"|"&C10&"|"&D10&"|"&E10,DUE_DATE_MASTER!I:I,DUE_DATE_MASTER!E:E,""),IF(B10="MONTH",DATE(VALUE(LEFT(C10,4)),VALUE(MID(C10,6,2))+1,20),IF(B10="QUARTER",DATE(YEAR(EOMONTH(INPUT!M16,0)),MONTH(EOMONTH(INPUT!M16,0))+1,IF(E10="A",22,24)),"")))) | I10: =IF(OR(G10="",H10=""),"",MAX(0,G10-H10)) | J10: =INPUT!H16 -> 0 | K10: =INPUT!I16 -> 0 | L10: =INPUT!J16 -> 0 | S10: =IF(P10="","",P10+Q10+R10)
A11: =INPUT!A17 -> 8 | B11: =INPUT!B17 -> 0 | C11: =INPUT!C17 -> 0 | D11: =INPUT!D17 -> 0 | E11: =INPUT!E17 -> 0 | F11: =INPUT!F17 -> NA | G11: =INPUT!G17 -> 0 | H11: =IF(C11="","",IFERROR(_xludf.XLOOKUP(B11&"|"&C11&"|"&D11&"|"&E11,DUE_DATE_MASTER!I:I,DUE_DATE_MASTER!E:E,""),IF(B11="MONTH",DATE(VALUE(LEFT(C11,4)),VALUE(MID(C11,6,2))+1,20),IF(B11="QUARTER",DATE(YEAR(EOMONTH(INPUT!M17,0)),MONTH(EOMONTH(INPUT!M17,0))+1,IF(E11="A",22,24)),"")))) | I11: =IF(OR(G11="",H11=""),"",MAX(0,G11-H11)) | J11: =INPUT!H17 -> 0 | K11: =INPUT!I17 -> 0 | L11: =INPUT!J17 -> 0 | S11: =IF(P11="","",P11+Q11+R11)
A12: =INPUT!A18 -> 9 | B12: =INPUT!B18 -> 0 | C12: =INPUT!C18 -> 0 | D12: =INPUT!D18 -> 0 | E12: =INPUT!E18 -> 0 | F12: =INPUT!F18 -> NA | G12: =INPUT!G18 -> 0 | H12: =IF(C12="","",IFERROR(_xludf.XLOOKUP(B12&"|"&C12&"|"&D12&"|"&E12,DUE_DATE_MASTER!I:I,DUE_DATE_MASTER!E:E,""),IF(B12="MONTH",DATE(VALUE(LEFT(C12,4)),VALUE(MID(C12,6,2))+1,20),IF(B12="QUARTER",DATE(YEAR(EOMONTH(INPUT!M18,0)),MONTH(EOMONTH(INPUT!M18,0))+1,IF(E12="A",22,24)),"")))) | I12: =IF(OR(G12="",H12=""),"",MAX(0,G12-H12)) | J12: =INPUT!H18 -> 0 | K12: =INPUT!I18 -> 0 | L12: =INPUT!J18 -> 0 | S12: =IF(P12="","",P12+Q12+R12)
A13: =INPUT!A19 -> 10 | B13: =INPUT!B19 -> 0 | C13: =INPUT!C19 -> 0 | D13: =INPUT!D19 -> 0 | E13: =INPUT!E19 -> 0 | F13: =INPUT!F19 -> NA | G13: =INPUT!G19 -> 0 | H13: =IF(C13="","",IFERROR(_xludf.XLOOKUP(B13&"|"&C13&"|"&D13&"|"&E13,DUE_DATE_MASTER!I:I,DUE_DATE_MASTER!E:E,""),IF(B13="MONTH",DATE(VALUE(LEFT(C13,4)),VALUE(MID(C13,6,2))+1,20),IF(B13="QUARTER",DATE(YEAR(EOMONTH(INPUT!M19,0)),MONTH(EOMONTH(INPUT!M19,0))+1,IF(E13="A",22,24)),"")))) | I13: =IF(OR(G13="",H13=""),"",MAX(0,G13-H13)) | J13: =INPUT!H19 -> 0 | K13: =INPUT!I19 -> 0 | L13: =INPUT!J19 -> 0 | S13: =IF(P13="","",P13+Q13+R13)
A14: =INPUT!A20 -> 11 | B14: =INPUT!B20 -> 0 | C14: =INPUT!C20 -> 0 | D14: =INPUT!D20 -> 0 | E14: =INPUT!E20 -> 0 | F14: =INPUT!F20 -> NA | G14: =INPUT!G20 -> 0 | H14: =IF(C14="","",IFERROR(_xludf.XLOOKUP(B14&"|"&C14&"|"&D14&"|"&E14,DUE_DATE_MASTER!I:I,DUE_DATE_MASTER!E:E,""),IF(B14="MONTH",DATE(VALUE(LEFT(C14,4)),VALUE(MID(C14,6,2))+1,20),IF(B14="QUARTER",DATE(YEAR(EOMONTH(INPUT!M20,0)),MONTH(EOMONTH(INPUT!M20,0))+1,IF(E14="A",22,24)),"")))) | I14: =IF(OR(G14="",H14=""),"",MAX(0,G14-H14)) | J14: =INPUT!H20 -> 0 | K14: =INPUT!I20 -> 0 | L14: =INPUT!J20 -> 0 | S14: =IF(P14="","",P14+Q14+R14)
A15: =INPUT!A21 -> 12 | B15: =INPUT!B21 -> 0 | C15: =INPUT!C21 -> 0 | D15: =INPUT!D21 -> 0 | E15: =INPUT!E21 -> 0 | F15: =INPUT!F21 -> NA | G15: =INPUT!G21 -> 0 | H15: =IF(C15="","",IFERROR(_xludf.XLOOKUP(B15&"|"&C15&"|"&D15&"|"&E15,DUE_DATE_MASTER!I:I,DUE_DATE_MASTER!E:E,""),IF(B15="MONTH",DATE(VALUE(LEFT(C15,4)),VALUE(MID(C15,6,2))+1,20),IF(B15="QUARTER",DATE(YEAR(EOMONTH(INPUT!M21,0)),MONTH(EOMONTH(INPUT!M21,0))+1,IF(E15="A",22,24)),"")))) | I15: =IF(OR(G15="",H15=""),"",MAX(0,G15-H15)) | J15: =INPUT!H21 -> 0 | K15: =INPUT!I21 -> 0 | L15: =INPUT!J21 -> 0 | S15: =IF(P15="","",P15+Q15+R15)
... A63: =INPUT!A69 -> 60 | B63: =INPUT!B69 -> 0 | C63: =INPUT!C69 -> 0 | D63: =INPUT!D69 -> 0 | E63: =INPUT!E69 -> 0 | F63: =INPUT!F69 -> NA | G63: =INPUT!G69 -> 0 | H63: =IF(C63="","",IFERROR(_xludf.XLOOKUP(B63&"|"&C63&"|"&D63&"|"&E63,DUE_DATE_MASTER!I:I,DUE_DATE_MASTER!E:E,""),IF(B63="MONTH",DATE(VALUE(LEFT(C63,4)),VALUE(MID(C63,6,2))+1,20),IF(B63="QUARTER",DATE(YEAR(EOMONTH(INPUT!M69,0)),MONTH(EOMONTH(INPUT!M69,0))+1,IF(E63="A",22,24)),"")))) | I63: =IF(OR(G63="",H63=""),"",MAX(0,G63-H63)) | J63: =INPUT!H69 -> 0 | K63: =INPUT!I69 -> 0 | L63: =INPUT!J69 -> 0 | S63: =IF(P63="","",P63+Q63+R63)

Sheet OUTPUT
A1: SUMMARY OUTPUT
A3: Totals (all rows in INPUT):
A5: Total IGST Interest | B5: =SUM(CALC!P:P) -> 0
A6: Total CGST Interest | B6: =SUM(CALC!Q:Q) -> 0
A7: Total SGST Interest | B7: =SUM(CALC!R:R) -> 0
A8: Total Interest | B8: =SUM(CALC!S:S) -> 0
A10: Periods late (count) | B10: =COUNTIF(CALC!I:I,">0") -> 0
A12: Advisory:
A13: • Interest computed on cash-paid IGST/CGST/SGST with filing date as payment proxy.
A14: • Maintain DUE_DATE_MASTER and INTEREST_RELIEF_RULES to cover all CBIC extensions/reliefs for Jul-2017 to Dec-2025.
A15: • Late fee waivers do not automatically waive interest unless explicitly notified.
